{"_id":"lodash._htmlescapes","_rev":"30-a8ac121503db69cc98f3ccbd52cf314a","name":"lodash._htmlescapes","description":"The internal Lo-Dash variable `htmlEscapes` as a Node.js module generated by lodash-cli.","dist-tags":{"latest":"2.4.1"},"versions":{"2.0.0":{"name":"lodash._htmlescapes","version":"2.0.0","description":"The internal Lo-Dash variable `htmlEscapes` as a Node.js module generated by lodash-cli.","homepage":"http://lodash.com/custom-builds","license":"MIT","keywords":["customize","functional","lodash","performance","speed","util"],"author":{"name":"John-David Dalton","email":"john.david.dalton@gmail.com","url":"http://allyoucanleet.com/"},"contributors":[{"name":"John-David Dalton","email":"john.david.dalton@gmail.com","url":"http://allyoucanleet.com/"},{"name":"Blaine Bublitz","email":"blaine@iceddev.com","url":"http://iceddev.com/"},{"name":"Kit Cambridge","email":"github@kitcambridge.be","url":"http://kitcambridge.be/"},{"name":"Mathias Bynens","email":"mathias@qiwi.be","url":"http://mathiasbynens.be/"}],"bugs":{"url":"https://github.com/lodash/lodash-cli/issues"},"repository":{"type":"git","url":"https://github.com/lodash/lodash-cli.git"},"_id":"lodash._htmlescapes@2.0.0","dist":{"shasum":"e900ef9ca52f38cb32de0ea0753193f74be82cef","tarball":"https://registry.npmjs.org/lodash._htmlescapes/-/lodash._htmlescapes-2.0.0.tgz","integrity":"sha512-o2q6G8BuqHClp/u/wL+ClgqCUWF69M9V5/yr+6B8xfszY58pIvX8hPztlzPgmKuLLp/Xg4sFcoqB9j13YMj56Q==","signatures":[{"keyid":"SHA256:jl3bwswu80PjjokCgh0o2w5c2U4LhQAE57gj9cz1kzA","sig":"MEUCIQC3rtcZS0Lhrv888Z1t+rlM9tykGDno+mSczhP7ILNqPQIgJOfwsCoUZzA86waOFHk1wsE+XsTzkPtojQUdmrRmKKM="}]},"_from":".","_npmVersion":"1.3.8","_npmUser":{"name":"jdalton","email":"john.david.dalton@gmail.com"},"maintainers":[{"name":"jdalton","email":"john.david.dalton@gmail.com"},{"name":"kitcambridge","email":"github@kitcambridge.be"},{"name":"mathias","email":"mathias@qiwi.be"},{"name":"phated","email":"blaine@iceddev.com"}],"directories":{}},"2.1.0":{"name":"lodash._htmlescapes","version":"2.1.0","description":"The internal Lo-Dash variable `htmlEscapes` as a Node.js module generated by lodash-cli.","homepage":"http://lodash.com/custom-builds","license":"MIT","keywords":["functional","lodash","lodash-modularized","performance","speed","util"],"author":{"name":"John-David Dalton","email":"john.david.dalton@gmail.com","url":"http://allyoucanleet.com/"},"contributors":[{"name":"John-David Dalton","email":"john.david.dalton@gmail.com","url":"http://allyoucanleet.com/"},{"name":"Blaine Bublitz","email":"blaine@iceddev.com","url":"http://iceddev.com/"},{"name":"Kit Cambridge","email":"github@kitcambridge.be","url":"http://kitcambridge.be/"},{"name":"Mathias Bynens","email":"mathias@qiwi.be","url":"http://mathiasbynens.be/"}],"bugs":{"url":"https://github.com/lodash/lodash-cli/issues"},"repository":{"type":"git","url":"https://github.com/lodash/lodash-cli.git"},"_id":"lodash._htmlescapes@2.1.0","dist":{"shasum":"0d1e5f84bcbfefd252607628287c1bb1c9ecd517","tarball":"https://registry.npmjs.org/lodash._htmlescapes/-/lodash._htmlescapes-2.1.0.tgz","integrity":"sha512-S1hFO6qbbNOCOqpK3j2SHguz9cjL3u+W2KwdoAR5xgsNla6L2oF6BqBnCvvrTuT1ZkOAe8wiX7dry921iGUyFg==","signatures":[{"keyid":"SHA256:jl3bwswu80PjjokCgh0o2w5c2U4LhQAE57gj9cz1kzA","sig":"MEUCIQCfzV4T7UFazGN6ht2dG7Umrhcj9jYvG6gGfvNfE94qAgIgH1zsF/h/7zhgRDM8/hi3oUS5CABFrt/jMXxJTDoWFcI="}]},"_from":".","_npmVersion":"1.3.8","_npmUser":{"name":"jdalton","email":"john.david.dalton@gmail.com"},"maintainers":[{"name":"jdalton","email":"john.david.dalton@gmail.com"},{"name":"kitcambridge","email":"github@kitcambridge.be"},{"name":"mathias","email":"mathias@qiwi.be"},{"name":"phated","email":"blaine@iceddev.com"}]},"2.2.0":{"name":"lodash._htmlescapes","version":"2.2.0","description":"The internal Lo-Dash variable `htmlEscapes` as a Node.js module generated by lodash-cli.","homepage":"http://lodash.com/custom-builds","license":"MIT","author":{"name":"John-David Dalton","email":"john.david.dalton@gmail.com","url":"http://allyoucanleet.com/"},"contributors":[{"name":"John-David Dalton","email":"john.david.dalton@gmail.com","url":"http://allyoucanleet.com/"},{"name":"Blaine Bublitz","email":"blaine@iceddev.com","url":"http://iceddev.com/"},{"name":"Kit Cambridge","email":"github@kitcambridge.be","url":"http://kitcambridge.be/"},{"name":"Mathias Bynens","email":"mathias@qiwi.be","url":"http://mathiasbynens.be/"}],"bugs":{"url":"https://github.com/lodash/lodash-cli/issues"},"repository":{"type":"git","url":"https://github.com/lodash/lodash-cli.git"},"_id":"lodash._htmlescapes@2.2.0","dist":{"shasum":"d3c271d433a018f5dfc158aead82c0234494ee97","tarball":"https://registry.npmjs.org/lodash._htmlescapes/-/lodash._htmlescapes-2.2.0.tgz","integrity":"sha512-vnr+IBTPXmPzjP07NRXWDmuU+uyzVgmZoGmqoK7wsiW+NwUY4Dkog8IWKIC8Qm7LDThTyEF6/E8Z33EImjVUlA==","signatures":[{"keyid":"SHA256:jl3bwswu80PjjokCgh0o2w5c2U4LhQAE57gj9cz1kzA","sig":"MEUCICWprDQzeEPhpNJjjyf4u9SN0VWGmsgCcicF994XDDLhAiEAhFBSEHp9b68oiNKVGLO9IizvsN0QZf67uj6vmvnFFxw="}]},"_from":".","_npmVersion":"1.3.8","_npmUser":{"name":"jdalton","email":"john.david.dalton@gmail.com"},"maintainers":[{"name":"jdalton","email":"john.david.dalton@gmail.com"},{"name":"kitcambridge","email":"github@kitcambridge.be"},{"name":"mathias","email":"mathias@qiwi.be"},{"name":"phated","email":"blaine@iceddev.com"}]},"2.2.1":{"name":"lodash._htmlescapes","version":"2.2.1","description":"The internal Lo-Dash variable `htmlEscapes` as a Node.js module generated by lodash-cli.","homepage":"http://lodash.com/custom-builds","license":"MIT","author":{"name":"John-David Dalton","email":"john.david.dalton@gmail.com","url":"http://allyoucanleet.com/"},"contributors":[{"name":"John-David Dalton","email":"john.david.dalton@gmail.com","url":"http://allyoucanleet.com/"},{"name":"Blaine Bublitz","email":"blaine@iceddev.com","url":"http://iceddev.com/"},{"name":"Kit Cambridge","email":"github@kitcambridge.be","url":"http://kitcambridge.be/"},{"name":"Mathias Bynens","email":"mathias@qiwi.be","url":"http://mathiasbynens.be/"}],"bugs":{"url":"https://github.com/lodash/lodash-cli/issues"},"repository":{"type":"git","url":"https://github.com/lodash/lodash-cli.git"},"_id":"lodash._htmlescapes@2.2.1","dist":{"shasum":"33f381a690d33b81e50642895fe5e6e6c04cfeb1","tarball":"https://registry.npmjs.org/lodash._htmlescapes/-/lodash._htmlescapes-2.2.1.tgz","integrity":"sha512-VKYnqqGtM3vc6t7lZB0FdG5keisVrSf4jA005qnfTpHCEezAHD8Mgn+uAswwD+0qKAd1ZZicl8kPgI+2uV6DMw==","signatures":[{"keyid":"SHA256:jl3bwswu80PjjokCgh0o2w5c2U4LhQAE57gj9cz1kzA","sig":"MEUCIQD+ujXzDdM/H0eysCVRXnU+1YMg6oS6xgHI8C4e5I3zoAIgWKjEU2ffQytq1UezFhkxBXNUbiOrmMJGliOEbQPHXGg="}]},"_from":".","_npmVersion":"1.3.11","_npmUser":{"name":"jdalton","email":"john.david.dalton@gmail.com"},"maintainers":[{"name":"jdalton","email":"john.david.dalton@gmail.com"},{"name":"kitcambridge","email":"github@kitcambridge.be"},{"name":"mathias","email":"mathias@qiwi.be"},{"name":"phated","email":"blaine@iceddev.com"}]},"2.3.0":{"name":"lodash._htmlescapes","version":"2.3.0","description":"The internal Lo-Dash variable `htmlEscapes` as a Node.js module generated by lodash-cli.","homepage":"http://lodash.com/custom-builds","license":"MIT","author":{"name":"John-David Dalton","email":"john.david.dalton@gmail.com","url":"http://allyoucanleet.com/"},"contributors":[{"name":"John-David Dalton","email":"john.david.dalton@gmail.com","url":"http://allyoucanleet.com/"},{"name":"Blaine Bublitz","email":"blaine@iceddev.com","url":"http://www.iceddev.com/"},{"name":"Kit Cambridge","email":"github@kitcambridge.be","url":"http://kitcambridge.be/"},{"name":"Mathias Bynens","email":"mathias@qiwi.be","url":"http://mathiasbynens.be/"}],"bugs":{"url":"https://github.com/lodash/lodash-cli/issues"},"repository":{"type":"git","url":"https://github.com/lodash/lodash-cli.git"},"_id":"lodash._htmlescapes@2.3.0","dist":{"shasum":"1ca98863cadf1fa1d82c84f35f31e40556a04f3a","tarball":"https://registry.npmjs.org/lodash._htmlescapes/-/lodash._htmlescapes-2.3.0.tgz","integrity":"sha512-tcYVRAKK/PJt7XvXs9cQF88GFRDRkJ6B7wVVs5dgzoiTDwNBa5F/VVThQXnoxHKugCmZsSVwNGtiyNE8ciuBAA==","signatures":[{"keyid":"SHA256:jl3bwswu80PjjokCgh0o2w5c2U4LhQAE57gj9cz1kzA","sig":"MEYCIQDjfJHGVORvQ/9ZznkSualFUlHmGDJDCsy05Md4SAr57wIhAMqc8GF9VLybEo8DsGAuJkzS5mLnE9Cj8TKBlNAkYjaX"}]},"_from":".","_npmVersion":"1.3.11","_npmUser":{"name":"jdalton","email":"john.david.dalton@gmail.com"},"maintainers":[{"name":"jdalton","email":"john.david.dalton@gmail.com"},{"name":"kitcambridge","email":"github@kitcambridge.be"},{"name":"mathias","email":"mathias@qiwi.be"},{"name":"phated","email":"blaine@iceddev.com"}]},"2.4.0":{"name":"lodash._htmlescapes","version":"2.4.0","description":"The internal Lo-Dash variable `htmlEscapes` as a Node.js module generated by lodash-cli.","homepage":"http://lodash.com/custom-builds","license":"MIT","author":{"name":"John-David Dalton","email":"john.david.dalton@gmail.com","url":"http://allyoucanleet.com/"},"contributors":[{"name":"John-David Dalton","email":"john.david.dalton@gmail.com","url":"http://allyoucanleet.com/"},{"name":"Blaine Bublitz","email":"blaine@iceddev.com","url":"http://www.iceddev.com/"},{"name":"Kit Cambridge","email":"github@kitcambridge.be","url":"http://kitcambridge.be/"},{"name":"Mathias Bynens","email":"mathias@qiwi.be","url":"http://mathiasbynens.be/"}],"bugs":{"url":"https://github.com/lodash/lodash-cli/issues"},"repository":{"type":"git","url":"https://github.com/lodash/lodash-cli.git"},"_id":"lodash._htmlescapes@2.4.0","dist":{"shasum":"f1edc87c30829468e18a9578ceb213fddb7fcf87","tarball":"https://registry.npmjs.org/lodash._htmlescapes/-/lodash._htmlescapes-2.4.0.tgz","integrity":"sha512-QLEwAWfkoWe3nxZ3/diSQ3s2kzz9VsNrgOAmKtgJbwNUASKNqRoZpHCBMhNUrblLHzG7qU/35FVi/3EqpSqj9A==","signatures":[{"keyid":"SHA256:jl3bwswu80PjjokCgh0o2w5c2U4LhQAE57gj9cz1kzA","sig":"MEUCIDKLQNzi5Jvc4H5xn2ePrFCr+npds5ui1+fH5PAqBeoYAiEAxrL3DrxZ1qYiOPO8ktde0SV2nnHYjL47NqJPMWg0Lms="}]},"_from":".","_npmVersion":"1.3.14","_npmUser":{"name":"jdalton","email":"john.david.dalton@gmail.com"},"maintainers":[{"name":"jdalton","email":"john.david.dalton@gmail.com"},{"name":"kitcambridge","email":"github@kitcambridge.be"},{"name":"mathias","email":"mathias@qiwi.be"},{"name":"phated","email":"blaine@iceddev.com"}]},"2.4.1":{"name":"lodash._htmlescapes","version":"2.4.1","description":"The internal Lo-Dash variable `htmlEscapes` as a Node.js module generated by lodash-cli.","homepage":"http://lodash.com/custom-builds","license":"MIT","author":{"name":"John-David Dalton","email":"john.david.dalton@gmail.com","url":"http://allyoucanleet.com/"},"contributors":[{"name":"John-David Dalton","email":"john.david.dalton@gmail.com","url":"http://allyoucanleet.com/"},{"name":"Blaine Bublitz","email":"blaine@iceddev.com","url":"http://www.iceddev.com/"},{"name":"Kit Cambridge","email":"github@kitcambridge.be","url":"http://kitcambridge.be/"},{"name":"Mathias Bynens","email":"mathias@qiwi.be","url":"http://mathiasbynens.be/"}],"bugs":{"url":"https://github.com/lodash/lodash-cli/issues"},"repository":{"type":"git","url":"https://github.com/lodash/lodash-cli.git"},"_id":"lodash._htmlescapes@2.4.1","dist":{"shasum":"32d14bf0844b6de6f8b62a051b4f67c228b624cb","tarball":"https://registry.npmjs.org/lodash._htmlescapes/-/lodash._htmlescapes-2.4.1.tgz","integrity":"sha512-g79hNmMOBVyV+4oKIHM7MWy9Awtk3yqf0Twlawr6f+CmG44nTwBh9I5XiLUnk39KTfYoDBpS66glQGgQCnFIuA==","signatures":[{"keyid":"SHA256:jl3bwswu80PjjokCgh0o2w5c2U4LhQAE57gj9cz1kzA","sig":"MEYCIQC+k5mTL0qj4FqIsrdhZT5SsbpH6YngSRcYfV00xfzJZQIhAPwviOxA0MxA8pPWOzoYxl7e1GIAWHDYADu8H+NYeHdu"}]},"_from":".","_npmVersion":"1.3.14","_npmUser":{"name":"jdalton","email":"john.david.dalton@gmail.com"},"maintainers":[{"name":"jdalton","email":"john.david.dalton@gmail.com"},{"name":"kitcambridge","email":"github@kitcambridge.be"},{"name":"mathias","email":"mathias@qiwi.be"},{"name":"phated","email":"blaine@iceddev.com"}]}},"readme":"# lodash._htmlescapes v2.4.1\n\nThe internal [Lo-Dash](http://lodash.com/) variable `htmlEscapes` as a [Node.js](http://nodejs.org/) module generated by [lodash-cli](https://npmjs.org/package/lodash-cli).\n\n## Author\n\n| [![twitter/jdalton](http://gravatar.com/avatar/299a3d891ff1920b69c364d061007043?s=70)](https://twitter.com/jdalton \"Follow @jdalton on Twitter\") |\n|---|\n| [John-David Dalton](http://allyoucanleet.com/) |\n\n## Contributors\n\n| [![twitter/blainebublitz](http://gravatar.com/avatar/ac1c67fd906c9fecd823ce302283b4c1?s=70)](https://twitter.com/blainebublitz \"Follow @BlaineBublitz on Twitter\") | [![twitter/kitcambridge](http://gravatar.com/avatar/6662a1d02f351b5ef2f8b4d815804661?s=70)](https://twitter.com/kitcambridge \"Follow @kitcambridge on Twitter\") | [![twitter/mathias](http://gravatar.com/avatar/24e08a9ea84deb17ae121074d0f17125?s=70)](https://twitter.com/mathias \"Follow @mathias on Twitter\") |\n|---|---|---|\n| [Blaine Bublitz](http://www.iceddev.com/) | [Kit Cambridge](http://kitcambridge.be/) | [Mathias Bynens](http://mathiasbynens.be/) |\n","maintainers":[{"name":"jdalton","email":"john.david.dalton@gmail.com"},{"name":"mathias","email":"mathias@qiwi.be"}],"time":{"modified":"2022-06-19T13:32:49.515Z","created":"2013-09-23T06:28:03.571Z","2.0.0":"2013-09-23T07:28:22.671Z","2.1.0":"2013-09-23T07:48:13.265Z","2.2.0":"2013-09-29T22:06:19.998Z","2.2.1":"2013-10-03T18:47:27.237Z","2.3.0":"2013-11-11T16:44:33.742Z","2.4.0":"2013-11-26T19:53:58.205Z","2.4.1":"2013-12-03T17:08:51.013Z"},"author":{"name":"John-David Dalton","email":"john.david.dalton@gmail.com","url":"http://allyoucanleet.com/"},"repository":{"type":"git","url":"https://github.com/lodash/lodash-cli.git"},"homepage":"http://lodash.com/custom-builds","contributors":[{"name":"John-David Dalton","email":"john.david.dalton@gmail.com","url":"http://allyoucanleet.com/"},{"name":"Blaine Bublitz","email":"blaine@iceddev.com","url":"http://www.iceddev.com/"},{"name":"Kit Cambridge","email":"github@kitcambridge.be","url":"http://kitcambridge.be/"},{"name":"Mathias Bynens","email":"mathias@qiwi.be","url":"http://mathiasbynens.be/"}],"bugs":{"url":"https://github.com/lodash/lodash-cli/issues"},"license":"MIT","readmeFilename":"README.md","_etag":"W/\"68eb0e672e1335fcb83bd880856ca9f3\"","_lastModified":"Sun, 19 Jun 2022 13:32:50 GMT"}