{"_id":"gulp-csso","_rev":"146-3cab18f751b82a585ad2baeac820bfba","name":"gulp-csso","description":"Minify CSS with CSSO.","dist-tags":{"latest":"4.0.1"},"versions":{"0.1.0":{"name":"gulp-csso","version":"0.1.0","description":"Run csso with gulp.","license":"MIT","homepage":"https://github.com/ben-eb/gulp-csso","author":{"name":"Ben Briggs","email":"therealbenbriggs@hotmail.com","url":"http://beneb.info"},"repository":{"type":"git","url":"git://github.com/ben-eb/gulp-csso.git"},"keywords":["gulpplugin","css"],"dependencies":{"csso":"~1.3.10","event-stream":"~3.0.15"},"main":"index.js","bugs":{"url":"https://github.com/ben-eb/gulp-csso/issues"},"_id":"gulp-csso@0.1.0","dist":{"shasum":"5891bb1dbc7a7aecffbf6af4a90005a85e2d384f","tarball":"https://registry.npmjs.org/gulp-csso/-/gulp-csso-0.1.0.tgz","integrity":"sha512-GI419pbmlmUa10EAIp0kjFkMB6e5sTpQadHjQL/dw3tuWHqhsajLTyevfR5VJoFcMESxydBzCEjpP7lnOPOIwQ==","signatures":[{"keyid":"SHA256:jl3bwswu80PjjokCgh0o2w5c2U4LhQAE57gj9cz1kzA","sig":"MEYCIQDvBy/84Tgc1lH6jgGEPjz9GpHe/Ed6C/2CkbUY9hQwNgIhANgV4nHZQ+51LEBKsf7D04J81gMFpyFXB28B5WF/eFZk"}]},"_from":".","_npmVersion":"1.3.11","_npmUser":{"name":"beneb","email":"therealbenbriggs@hotmail.com"},"maintainers":[{"name":"beneb","email":"therealbenbriggs@hotmail.com"}],"directories":{}},"0.1.1":{"name":"gulp-csso","version":"0.1.1","description":"Run csso with gulp.","license":"MIT","homepage":"https://github.com/ben-eb/gulp-csso","author":{"name":"Ben Briggs","email":"therealbenbriggs@hotmail.com","url":"http://beneb.info"},"repository":{"type":"git","url":"git://github.com/ben-eb/gulp-csso.git"},"keywords":["gulpplugin","css"],"dependencies":{"csso":"~1.3.10","event-stream":"~3.0.15"},"main":"index.js","bugs":{"url":"https://github.com/ben-eb/gulp-csso/issues"},"_id":"gulp-csso@0.1.1","dist":{"shasum":"d33c8fa78f13f1bad32e704b90ea0eadf7215d17","tarball":"https://registry.npmjs.org/gulp-csso/-/gulp-csso-0.1.1.tgz","integrity":"sha512-wewyf8B9X6AMUatwlyTQzJYp/pzBOh+JX9WoXc30MXpAiZxahoF2/Qjdqzw3gyp92fQYb0zuFCsMRG/CLWYpYg==","signatures":[{"keyid":"SHA256:jl3bwswu80PjjokCgh0o2w5c2U4LhQAE57gj9cz1kzA","sig":"MEUCIQDNdhB7vNjEntjdpdqZd0qc7IsFK6b1pftPdQxrr1gOpgIgMtbfBS48tuEGT8lAg9EXUAb3oWggu2I8KGxDoSy1qnA="}]},"_from":".","_npmVersion":"1.3.11","_npmUser":{"name":"beneb","email":"therealbenbriggs@hotmail.com"},"maintainers":[{"name":"beneb","email":"therealbenbriggs@hotmail.com"}],"directories":{}},"0.1.2":{"name":"gulp-csso","version":"0.1.2","description":"Minify CSS with CSSO.","license":"MIT","homepage":"https://github.com/ben-eb/gulp-csso","author":{"name":"Ben Briggs","email":"therealbenbriggs@hotmail.com","url":"http://beneb.info"},"scripts":{"test":"mocha"},"repository":{"type":"git","url":"git://github.com/ben-eb/gulp-csso.git"},"keywords":["gulpplugin","css"],"dependencies":{"csso":"~1.3.10","event-stream":"~3.0.15"},"devDependencies":{"chai":"~1.8.1","gulp-util":"~2.1.3","mocha":"~1.15.1"},"main":"index.js","bugs":{"url":"https://github.com/ben-eb/gulp-csso/issues"},"_id":"gulp-csso@0.1.2","dist":{"shasum":"fb1f11cc6f1f9851424e76671bac51f978bdfa02","tarball":"https://registry.npmjs.org/gulp-csso/-/gulp-csso-0.1.2.tgz","integrity":"sha512-Guw5ZgKUs1/s6+Bczaxy5w8Ys4DyNpsVtxsXE6kGlYMiSxwiNah/SOJSYahktA1764cKVcERuiG1vhhiO6GiZQ==","signatures":[{"keyid":"SHA256:jl3bwswu80PjjokCgh0o2w5c2U4LhQAE57gj9cz1kzA","sig":"MEQCIAGgo+0+kGrwitTJwNATNEeqHlFIDczu0K0UZhg5MknqAiBcAESKNBAeYEZ19C/z3Hbld9SlmICVEc1mHG8X2kVFFg=="}]},"_from":".","_npmVersion":"1.3.11","_npmUser":{"name":"beneb","email":"therealbenbriggs@hotmail.com"},"maintainers":[{"name":"beneb","email":"therealbenbriggs@hotmail.com"}],"directories":{}},"0.1.3":{"name":"gulp-csso","version":"0.1.3","description":"Minify CSS with CSSO.","license":"MIT","homepage":"https://github.com/ben-eb/gulp-csso","author":{"name":"Ben Briggs","email":"therealbenbriggs@hotmail.com","url":"http://beneb.info"},"scripts":{"test":"mocha"},"repository":{"type":"git","url":"git://github.com/ben-eb/gulp-csso.git"},"keywords":["gulpplugin","css"],"dependencies":{"csso":"~1.3.10","event-stream":"~3.0.15"},"devDependencies":{"chai":"~1.8.1","gulp-util":"~2.1.3","mocha":"~1.15.1"},"main":"index.js","bugs":{"url":"https://github.com/ben-eb/gulp-csso/issues"},"_id":"gulp-csso@0.1.3","dist":{"shasum":"5ebd9f9bedd85978e7cc70fc3a727d52e142ac4b","tarball":"https://registry.npmjs.org/gulp-csso/-/gulp-csso-0.1.3.tgz","integrity":"sha512-kfw45vKZEX9For3e3X6m3t2JROfAwQ0SYYbivsTe1LEdYXPA0dfJoKpO4s5V3exVHEZvDIKCZws2TTO/18BYMA==","signatures":[{"keyid":"SHA256:jl3bwswu80PjjokCgh0o2w5c2U4LhQAE57gj9cz1kzA","sig":"MEUCIQDCBV00wzVSVxYvb8GBRxI+Vpo+HdhhmD5f4uGsLAj8AwIgRk1tGffSrQCI22EU8hfVFlcme4xZcg7Omcmvwu4vPGM="}]},"_from":".","_npmVersion":"1.3.21","_npmUser":{"name":"beneb","email":"therealbenbriggs@hotmail.com"},"maintainers":[{"name":"beneb","email":"therealbenbriggs@hotmail.com"}],"directories":{}},"0.1.4":{"name":"gulp-csso","version":"0.1.4","description":"Minify CSS with CSSO.","license":"MIT","homepage":"https://github.com/ben-eb/gulp-csso","author":{"name":"Ben Briggs","email":"therealbenbriggs@hotmail.com","url":"http://beneb.info"},"scripts":{"test":"mocha"},"repository":{"type":"git","url":"git://github.com/ben-eb/gulp-csso.git"},"keywords":["gulpplugin","css"],"dependencies":{"csso":"~1.3.10","map-stream":"0.0.4"},"devDependencies":{"chai":"~1.8.1","gulp-util":"~2.1.3","mocha":"~1.15.1"},"main":"index.js","bugs":{"url":"https://github.com/ben-eb/gulp-csso/issues"},"_id":"gulp-csso@0.1.4","dist":{"shasum":"44ca1b4694141a6b8bc5f80c1453bc4089466031","tarball":"https://registry.npmjs.org/gulp-csso/-/gulp-csso-0.1.4.tgz","integrity":"sha512-AgqTr0p/a9F4fg5BTPpPrGbempHophnohPH4oCvORJpNVKfn2JC3I7BYq2EnkEBe6KMGnoUg7n7+1tn04FozLA==","signatures":[{"keyid":"SHA256:jl3bwswu80PjjokCgh0o2w5c2U4LhQAE57gj9cz1kzA","sig":"MEYCIQCdfue3ugsHpqbQiFgmqmrYwzWSA834NOnTnuZ9RXIm3AIhANMD1PWLr+WOF9bF4tMT5U8B8qYsxVTHXtf+eYaGiqyv"}]},"_from":".","_npmVersion":"1.3.21","_npmUser":{"name":"beneb","email":"therealbenbriggs@hotmail.com"},"maintainers":[{"name":"beneb","email":"therealbenbriggs@hotmail.com"}],"directories":{}},"0.1.5":{"name":"gulp-csso","version":"0.1.5","description":"Minify CSS with CSSO.","license":"MIT","homepage":"https://github.com/ben-eb/gulp-csso","author":{"name":"Ben Briggs","email":"therealbenbriggs@hotmail.com","url":"http://beneb.info"},"scripts":{"test":"mocha"},"repository":{"type":"git","url":"git://github.com/ben-eb/gulp-csso.git"},"keywords":["gulpplugin","css"],"dependencies":{"csso":"~1.3.10","map-stream":"0.0.4"},"devDependencies":{"chai":"~1.8.1","gulp-util":"~2.1.3","mocha":"~1.15.1"},"main":"index.js","bugs":{"url":"https://github.com/ben-eb/gulp-csso/issues"},"_id":"gulp-csso@0.1.5","dist":{"shasum":"75827d8d5bc98459860e42ff6799ccb9ebf4e8ee","tarball":"https://registry.npmjs.org/gulp-csso/-/gulp-csso-0.1.5.tgz","integrity":"sha512-cZhUZvi2r28q1spNQFAzW9leAHm46uVYSgaRQSs/Vp2M5Qwwf33tUHQujkLQaq3VZ1QXmUkjU5kkDtsdpmwK+w==","signatures":[{"keyid":"SHA256:jl3bwswu80PjjokCgh0o2w5c2U4LhQAE57gj9cz1kzA","sig":"MEUCIGzkJACWo8plB8bvm5EgePMAtyd5TzoGY8byf2c3YItkAiEAs0jG1jMChF/Geb8vLdHntgiRSFnrajS567sVa4+nJJo="}]},"_from":".","_npmVersion":"1.3.21","_npmUser":{"name":"beneb","email":"therealbenbriggs@hotmail.com"},"maintainers":[{"name":"beneb","email":"therealbenbriggs@hotmail.com"}],"directories":{}},"0.1.6":{"name":"gulp-csso","version":"0.1.6","description":"Minify CSS with CSSO.","license":"MIT","homepage":"https://github.com/ben-eb/gulp-csso","author":{"name":"Ben Briggs","email":"therealbenbriggs@hotmail.com","url":"http://beneb.info"},"scripts":{"test":"mocha"},"repository":{"type":"git","url":"git://github.com/ben-eb/gulp-csso.git"},"keywords":["gulpplugin","css"],"dependencies":{"csso":"~1.3.10","map-stream":"0.0.4"},"devDependencies":{"chai":"~1.8.1","clear":"0.0.1","gulp":"~3.2.3","gulp-mocha":"~0.2.0","gulp-jshint":"~1.3.4","gulp-util":"~2.2.5","jshint-stylish":"~0.1.5","mocha":"~1.16.2"},"main":"index.js","bugs":{"url":"https://github.com/ben-eb/gulp-csso/issues"},"_id":"gulp-csso@0.1.6","dist":{"shasum":"14045751371744658af7c0a87315535d80b7a077","tarball":"https://registry.npmjs.org/gulp-csso/-/gulp-csso-0.1.6.tgz","integrity":"sha512-iWV6BEdO+mjPk1mgC9B8wzcqjb9UTTyD5RrVOOHUW5iNi+YtmwJwP1+nZq3wm33k2Ryb1lpUpKzCt0CiDJxbeQ==","signatures":[{"keyid":"SHA256:jl3bwswu80PjjokCgh0o2w5c2U4LhQAE57gj9cz1kzA","sig":"MEYCIQCDLYsjPbFUS7Zcqk3e8Pd9hT6qtQICtAVRWDLE8DcHkAIhAPPzSYTtuYl2wcvaFJJEjNtODzjEsIDkV05hjaabfAt7"}]},"_from":".","_npmVersion":"1.3.21","_npmUser":{"name":"beneb","email":"therealbenbriggs@hotmail.com"},"maintainers":[{"name":"beneb","email":"therealbenbriggs@hotmail.com"}],"directories":{}},"0.1.7":{"name":"gulp-csso","version":"0.1.7","description":"Minify CSS with CSSO.","license":"MIT","homepage":"https://github.com/ben-eb/gulp-csso","author":{"name":"Ben Briggs","email":"therealbenbriggs@hotmail.com","url":"http://beneb.info"},"scripts":{"test":"mocha"},"repository":{"type":"git","url":"git://github.com/ben-eb/gulp-csso.git"},"keywords":["gulpplugin","css"],"dependencies":{"csso":"~1.3.10","map-stream":"0.0.4"},"devDependencies":{"chai":"~1.8.1","clear":"0.0.1","gulp":"~3.2.3","gulp-mocha":"~0.2.0","gulp-jshint":"~1.3.4","gulp-util":"~2.2.6","jshint-stylish":"~0.1.5","mocha":"~1.16.2"},"main":"index.js","bugs":{"url":"https://github.com/ben-eb/gulp-csso/issues"},"_id":"gulp-csso@0.1.7","dist":{"shasum":"82e0e2148ad25d87ec0876c53c4d8810234927d6","tarball":"https://registry.npmjs.org/gulp-csso/-/gulp-csso-0.1.7.tgz","integrity":"sha512-wCWUFFULdsHLaBPHkWmPJNLPw7nKfTwMJZry93f2PSMQUj+uxcL7gYH7DIfkZwHC6dzpVh63VXE5quMQZresxA==","signatures":[{"keyid":"SHA256:jl3bwswu80PjjokCgh0o2w5c2U4LhQAE57gj9cz1kzA","sig":"MEUCIC1fQQM99UzJpNigJCUhOmE+wqy/u1uzE6014OA6GRGmAiEA1QqMKj7uzxwRSn9TXPzrINpRJMbEQXzUB3EHIsHQc9U="}]},"_from":".","_npmVersion":"1.3.21","_npmUser":{"name":"beneb","email":"therealbenbriggs@hotmail.com"},"maintainers":[{"name":"beneb","email":"therealbenbriggs@hotmail.com"}],"directories":{}},"0.1.8":{"name":"gulp-csso","version":"0.1.8","description":"Minify CSS with CSSO.","license":"MIT","homepage":"https://github.com/ben-eb/gulp-csso","author":{"name":"Ben Briggs","email":"therealbenbriggs@hotmail.com","url":"http://beneb.info"},"scripts":{"test":"mocha"},"repository":{"type":"git","url":"git://github.com/ben-eb/gulp-csso.git"},"keywords":["gulpplugin","css"],"dependencies":{"csso":"~1.3.10","map-stream":"~0.1.0"},"devDependencies":{"chai":"~1.8.1","clear":"0.0.1","gulp":"~3.2.3","gulp-mocha":"~0.2.0","gulp-jshint":"~1.3.4","gulp-util":"~2.2.6","jshint-stylish":"~0.1.5","mocha":"~1.16.2"},"main":"index.js","bugs":{"url":"https://github.com/ben-eb/gulp-csso/issues"},"_id":"gulp-csso@0.1.8","dist":{"shasum":"9e347b70d42015e6a0dc35187155891bebc67c60","tarball":"https://registry.npmjs.org/gulp-csso/-/gulp-csso-0.1.8.tgz","integrity":"sha512-uAAi9n7rk8ZQpzjaBzVgxP9Pj2xE5c1DOsBVkN6TAffo9fZJmSZhFh3vM9RfXL8svVfS59SRz0+dMqlk4RSDBw==","signatures":[{"keyid":"SHA256:jl3bwswu80PjjokCgh0o2w5c2U4LhQAE57gj9cz1kzA","sig":"MEUCIQCYAgMsBJ+oyeJzTDmSXm45mryqO50Dd/52D9wspfv7TwIgakxySIn0fBpCa515wNlaxS8PfVcoaPodqyDqaTGi+zM="}]},"_from":".","_npmVersion":"1.3.21","_npmUser":{"name":"beneb","email":"therealbenbriggs@hotmail.com"},"maintainers":[{"name":"beneb","email":"therealbenbriggs@hotmail.com"}],"directories":{}},"0.2.0":{"name":"gulp-csso","version":"0.2.0","description":"Minify CSS with CSSO.","license":"MIT","homepage":"https://github.com/ben-eb/gulp-csso","author":{"name":"Ben Briggs","email":"therealbenbriggs@hotmail.com","url":"http://beneb.info"},"scripts":{"test":"mocha"},"repository":{"type":"git","url":"git://github.com/ben-eb/gulp-csso.git"},"keywords":["gulpplugin","css"],"dependencies":{"csso":"~1.3.10","map-stream":"~0.1.0","bufferstreams":"0.0.1"},"devDependencies":{"chai":"~1.8.1","clear":"0.0.1","gulp":"~3.2.3","gulp-mocha":"~0.2.0","gulp-jshint":"~1.3.4","gulp-util":"~2.2.6","jshint-stylish":"~0.1.5","mocha":"~1.16.2","event-stream":"~3.1.0"},"main":"index.js","bugs":{"url":"https://github.com/ben-eb/gulp-csso/issues"},"_id":"gulp-csso@0.2.0","dist":{"shasum":"d24ac7807c43d0dc4af25be544330e995ea8460b","tarball":"https://registry.npmjs.org/gulp-csso/-/gulp-csso-0.2.0.tgz","integrity":"sha512-iECGwFlyFjFnHIt969D85w3nfLbqgPIOBD3eKsqNiCpBVMUNuCE/I73g2T24vGMbWavwoIqylE7pI7dRwwOSFQ==","signatures":[{"keyid":"SHA256:jl3bwswu80PjjokCgh0o2w5c2U4LhQAE57gj9cz1kzA","sig":"MEYCIQCsYSVA9wOJFZ62SEifNxAy0uEn9O1GPH1xh04Lll+aSgIhAJGL8oJcn2WRZs2tuQlMY3Q2mUTRwt1B5jF2qzb7WiJj"}]},"_from":".","_npmVersion":"1.3.21","_npmUser":{"name":"beneb","email":"therealbenbriggs@hotmail.com"},"maintainers":[{"name":"beneb","email":"therealbenbriggs@hotmail.com"}],"directories":{}},"0.2.1":{"name":"gulp-csso","version":"0.2.1","description":"Minify CSS with CSSO.","license":"MIT","homepage":"https://github.com/ben-eb/gulp-csso","author":{"name":"Ben Briggs","email":"therealbenbriggs@hotmail.com","url":"http://beneb.info"},"scripts":{"test":"mocha"},"repository":{"type":"git","url":"git://github.com/ben-eb/gulp-csso.git"},"keywords":["gulpplugin","css"],"dependencies":{"csso":"~1.3.10","map-stream":"~0.1.0","bufferstreams":"0.0.1"},"devDependencies":{"chai":"~1.8.1","clear":"0.0.1","gulp":"~3.2.3","gulp-mocha":"~0.2.0","gulp-jshint":"~1.3.4","gulp-util":"~2.2.6","jshint-stylish":"~0.1.5","mocha":"~1.16.2","event-stream":"~3.1.0"},"main":"index.js","bugs":{"url":"https://github.com/ben-eb/gulp-csso/issues"},"_id":"gulp-csso@0.2.1","dist":{"shasum":"20676b4c05dca7dcf66ee0f5628fb144c3069183","tarball":"https://registry.npmjs.org/gulp-csso/-/gulp-csso-0.2.1.tgz","integrity":"sha512-FyhPlpzUmu94aic94U1FflsFLemZiAMpz7S30VC0ubaKKzs9xn6BV5TW8m2Yn4wXq6BWSZ2lND/wsaJ8SVz+GA==","signatures":[{"keyid":"SHA256:jl3bwswu80PjjokCgh0o2w5c2U4LhQAE57gj9cz1kzA","sig":"MEQCIDC7K9LuhbD/BYGXNCbYF9+c2JpFyySgDorMPxsoc3UYAiBua3+fKFUIAboPyOj78yBXw7dg4vLUa1EjEEeitEwpHQ=="}]},"_from":".","_npmVersion":"1.3.21","_npmUser":{"name":"beneb","email":"therealbenbriggs@hotmail.com"},"maintainers":[{"name":"beneb","email":"therealbenbriggs@hotmail.com"}],"directories":{}},"0.2.2":{"name":"gulp-csso","version":"0.2.2","description":"Minify CSS with CSSO.","license":"MIT","homepage":"https://github.com/ben-eb/gulp-csso","author":{"name":"Ben Briggs","email":"therealbenbriggs@hotmail.com","url":"http://beneb.info"},"scripts":{"test":"mocha"},"repository":{"type":"git","url":"git://github.com/ben-eb/gulp-csso.git"},"keywords":["gulpplugin","minify","css"],"dependencies":{"csso":"~1.3.10","bufferstreams":"0.0.1"},"devDependencies":{"chai":"~1.8.1","clear":"0.0.1","gulp":"~3.2.3","gulp-mocha":"~0.2.0","gulp-jshint":"~1.3.4","gulp-util":"~2.2.6","jshint-stylish":"~0.1.5","mocha":"~1.16.2","event-stream":"~3.1.0"},"main":"index.js","bugs":{"url":"https://github.com/ben-eb/gulp-csso/issues"},"_id":"gulp-csso@0.2.2","dist":{"shasum":"ba465b4096d69721aa387629b5d3f5b31c6d2933","tarball":"https://registry.npmjs.org/gulp-csso/-/gulp-csso-0.2.2.tgz","integrity":"sha512-zyVzBpEodkr4KGG4ijOwWZzrBIH8hZ5LOBdnv6uy1VEfBSN8QjJf5cLY3Qz/igvFuwYqu2YG1mATGKaePlSTXg==","signatures":[{"keyid":"SHA256:jl3bwswu80PjjokCgh0o2w5c2U4LhQAE57gj9cz1kzA","sig":"MEUCIGgi+WH+V1JKn+4JtqdD9dDKTiiLYgTUC0Kl5mX60zL8AiEAmoW2ygLyn6U/8oriNp0S0v8GPtGS5ZT6rRU02kh7TVk="}]},"_from":".","_npmVersion":"1.3.21","_npmUser":{"name":"beneb","email":"therealbenbriggs@hotmail.com"},"maintainers":[{"name":"beneb","email":"therealbenbriggs@hotmail.com"}],"directories":{}},"0.2.3":{"name":"gulp-csso","version":"0.2.3","description":"Minify CSS with CSSO.","license":"MIT","homepage":"https://github.com/ben-eb/gulp-csso","author":{"name":"Ben Briggs","email":"therealbenbriggs@hotmail.com","url":"http://beneb.info"},"scripts":{"test":"mocha"},"repository":{"type":"git","url":"git://github.com/ben-eb/gulp-csso.git"},"keywords":["gulpplugin","minify","css"],"dependencies":{"csso":"~1.3.10","bufferstreams":"0.0.1","gulp-util":"~2.2.6"},"devDependencies":{"chai":"~1.8.1","clear":"0.0.1","gulp":"~3.2.3","gulp-mocha":"~0.2.0","gulp-jshint":"~1.3.4","jshint-stylish":"~0.1.5","mocha":"~1.16.2","event-stream":"~3.1.0"},"main":"index.js","bugs":{"url":"https://github.com/ben-eb/gulp-csso/issues"},"_id":"gulp-csso@0.2.3","dist":{"shasum":"6be190ff50af39b26e646ab49ee456050ec95740","tarball":"https://registry.npmjs.org/gulp-csso/-/gulp-csso-0.2.3.tgz","integrity":"sha512-TsmIokwRAziJwSrip3Ymyz7umeHEKFsndpa17Y+84QLw4QNVnyoeyCX11xe/ZO7AggvlYiscOdwRoe3fh3B8BQ==","signatures":[{"keyid":"SHA256:jl3bwswu80PjjokCgh0o2w5c2U4LhQAE57gj9cz1kzA","sig":"MEQCIAelBecAVFmT/4IQvXJCMPWS6x7kV1tUJvl1WKgxaooOAiAKK5Ok+RxCAqt14bXdHuQTxnhwmVZMvuXmTcWbbYZdLw=="}]},"_from":".","_npmVersion":"1.3.21","_npmUser":{"name":"beneb","email":"therealbenbriggs@hotmail.com"},"maintainers":[{"name":"beneb","email":"therealbenbriggs@hotmail.com"}],"directories":{}},"0.2.4":{"name":"gulp-csso","version":"0.2.4","description":"Minify CSS with CSSO.","license":"MIT","homepage":"https://github.com/ben-eb/gulp-csso","author":{"name":"Ben Briggs","email":"therealbenbriggs@hotmail.com","url":"http://beneb.info"},"scripts":{"test":"mocha"},"repository":{"type":"git","url":"git://github.com/ben-eb/gulp-csso.git"},"keywords":["gulpplugin","minify","css"],"dependencies":{"csso":"~1.3.10","bufferstreams":"0.0.1","gulp-util":"~2.2.6"},"devDependencies":{"chai":"~1.8.1","clear":"0.0.1","gulp":"~3.2.3","gulp-mocha":"~0.2.0","gulp-jshint":"~1.3.4","jshint-stylish":"~0.1.5","mocha":"~1.16.2","event-stream":"~3.1.0"},"main":"index.js","bugs":{"url":"https://github.com/ben-eb/gulp-csso/issues"},"_id":"gulp-csso@0.2.4","dist":{"shasum":"0c306617d44e588ce85ee4739bbdb61d98b68f55","tarball":"https://registry.npmjs.org/gulp-csso/-/gulp-csso-0.2.4.tgz","integrity":"sha512-PX0zQP6/IbiH0fM515HoOq+XsCWIj69wlau0qBPyzvkP0xXD6zQgC5feISyfEWILkNMgFK9pXuDrjuWMFqk79w==","signatures":[{"keyid":"SHA256:jl3bwswu80PjjokCgh0o2w5c2U4LhQAE57gj9cz1kzA","sig":"MEUCIQCF13GS0zGN83C9l0tDqpsOTSOiErqbiKu/Gj+cJMv6eQIgLWYOWaiHl5p7hqFKou421nBmVjzrAj2hGridXPqVdxE="}]},"_from":".","_npmVersion":"1.3.21","_npmUser":{"name":"beneb","email":"therealbenbriggs@hotmail.com"},"maintainers":[{"name":"beneb","email":"therealbenbriggs@hotmail.com"}],"directories":{}},"0.2.5":{"name":"gulp-csso","version":"0.2.5","description":"Minify CSS with CSSO.","license":"MIT","homepage":"https://github.com/ben-eb/gulp-csso","author":{"name":"Ben Briggs","email":"therealbenbriggs@hotmail.com","url":"http://beneb.info"},"scripts":{"test":"mocha"},"repository":{"type":"git","url":"git://github.com/ben-eb/gulp-csso.git"},"keywords":["gulpplugin","minify","css"],"dependencies":{"csso":"~1.3.11","bufferstreams":"0.0.1","gulp-util":"~2.2.6"},"devDependencies":{"chai":"~1.8.1","clear":"0.0.1","gulp":"~3.2.3","gulp-mocha":"~0.2.0","gulp-jshint":"~1.3.4","jshint-stylish":"~0.1.5","mocha":"~1.16.2","event-stream":"~3.1.0"},"main":"index.js","bugs":{"url":"https://github.com/ben-eb/gulp-csso/issues"},"_id":"gulp-csso@0.2.5","dist":{"shasum":"f31954737074ebeac78d9b106a654ebf234a54f8","tarball":"https://registry.npmjs.org/gulp-csso/-/gulp-csso-0.2.5.tgz","integrity":"sha512-ddW5iWsUjDegJhobEnhUMA+uo261Jij4LTjVrV4lhFB5EqWeFhZFF+yYL8CP9+OsmaBi1kNJpVuec9xCZbs1NA==","signatures":[{"keyid":"SHA256:jl3bwswu80PjjokCgh0o2w5c2U4LhQAE57gj9cz1kzA","sig":"MEUCIARVjRhoFWEfqFrGWElVDPj5n9K2MLGIBcMfrLD+T73bAiEA+tDSNuAGmQdAsw9O7HfLAEOHBTs2RJnE9WX1sLd03sg="}]},"_from":".","_npmVersion":"1.3.21","_npmUser":{"name":"beneb","email":"therealbenbriggs@hotmail.com"},"maintainers":[{"name":"beneb","email":"therealbenbriggs@hotmail.com"}],"directories":{}},"0.2.6":{"name":"gulp-csso","version":"0.2.6","description":"Minify CSS with CSSO.","license":"MIT","homepage":"https://github.com/ben-eb/gulp-csso","author":{"name":"Ben Briggs","email":"therealbenbriggs@hotmail.com","url":"http://beneb.info"},"scripts":{"test":"mocha"},"repository":{"type":"git","url":"git://github.com/ben-eb/gulp-csso.git"},"keywords":["gulpplugin","minify","css"],"dependencies":{"csso":"~1.3.11","bufferstreams":"0.0.1","gulp-util":"~2.2.14"},"devDependencies":{"chai":"~1.9.0","clear":"0.0.1","gulp":"~3.5.2","gulp-mocha":"~0.4.1","gulp-jshint":"~1.5.0","jshint-stylish":"~0.1.5","mocha":"~1.17.1","event-stream":"~3.1.0"},"main":"index.js","bugs":{"url":"https://github.com/ben-eb/gulp-csso/issues"},"_id":"gulp-csso@0.2.6","dist":{"shasum":"a9d65121c5b76e7f5fe45c699667cccd83db6d60","tarball":"https://registry.npmjs.org/gulp-csso/-/gulp-csso-0.2.6.tgz","integrity":"sha512-1h7zcDIkeYFjJdzdVWn/tw7czc9k7VEnayeIelKRNdTPX05fE4I43XBFo8fld4hJa3tj5HHdFSjKxRabmiRgGA==","signatures":[{"keyid":"SHA256:jl3bwswu80PjjokCgh0o2w5c2U4LhQAE57gj9cz1kzA","sig":"MEUCIDwynugTbJqycW3aNCtvGY5zyHrKBL7q88Zh+IkiBcbdAiEAl42fUZ0dDvhYo2M8kXuK8g6BIN4hUYqGxquxn0RqncU="}]},"_from":".","_npmVersion":"1.3.21","_npmUser":{"name":"beneb","email":"therealbenbriggs@hotmail.com"},"maintainers":[{"name":"beneb","email":"therealbenbriggs@hotmail.com"}],"directories":{}},"0.2.7":{"name":"gulp-csso","version":"0.2.7","description":"Minify CSS with CSSO.","license":"MIT","homepage":"https://github.com/ben-eb/gulp-csso","author":{"name":"Ben Briggs","email":"therealbenbriggs@hotmail.com","url":"http://beneb.info"},"scripts":{"test":"mocha"},"repository":{"type":"git","url":"git://github.com/ben-eb/gulp-csso.git"},"keywords":["gulpplugin","minify","css"],"dependencies":{"csso":"~1.3.11","bufferstreams":"0.0.1","gulp-util":"~2.2.14"},"devDependencies":{"chai":"~1.9.0","clear":"0.0.1","gulp":"~3.5.2","gulp-mocha":"~0.4.1","gulp-jshint":"~1.5.0","jshint-stylish":"~0.1.5","mocha":"~1.17.1","event-stream":"~3.1.0"},"main":"index.js","bugs":{"url":"https://github.com/ben-eb/gulp-csso/issues"},"_id":"gulp-csso@0.2.7","dist":{"shasum":"1a6720c1177a3d95b041bae725f9471905ff2f53","tarball":"https://registry.npmjs.org/gulp-csso/-/gulp-csso-0.2.7.tgz","integrity":"sha512-jUt35ZEE7K5CeNNIMqtkepbP1U7U0GUPmqHQxea1T61Ejg8YsoxP5l12YjVUjLJFnFSlBDDW4H2SgmE2xVf/zA==","signatures":[{"keyid":"SHA256:jl3bwswu80PjjokCgh0o2w5c2U4LhQAE57gj9cz1kzA","sig":"MEYCIQC58FNjxdd3rkX+RogbCKG8aKxMjX4kmLv0JSh46lbyUQIhAMrCb9d5wq7U2fAkNQ9V/TY0CH1eSz/rUEl5m+4h3Bn1"}]},"_from":".","_npmVersion":"1.3.21","_npmUser":{"name":"beneb","email":"therealbenbriggs@hotmail.com"},"maintainers":[{"name":"beneb","email":"therealbenbriggs@hotmail.com"}],"directories":{}},"0.2.8":{"name":"gulp-csso","version":"0.2.8","description":"Minify CSS with CSSO.","license":"MIT","homepage":"https://github.com/ben-eb/gulp-csso","author":{"name":"Ben Briggs","email":"therealbenbriggs@hotmail.com","url":"http://beneb.info"},"scripts":{"test":"mocha"},"repository":{"type":"git","url":"git://github.com/ben-eb/gulp-csso.git"},"keywords":["gulpplugin","minify","css"],"dependencies":{"csso":"~1.3.11","bufferstreams":"0.0.1","gulp-util":"~2.2.14"},"devDependencies":{"chai":"~1.9.0","clear":"0.0.1","gulp":"~3.6.1","gulp-mocha":"~0.4.1","gulp-jshint":"~1.5.0","jshint-stylish":"~0.1.5","mocha":"~1.18.2","event-stream":"~3.1.0"},"main":"index.js","bugs":{"url":"https://github.com/ben-eb/gulp-csso/issues"},"_id":"gulp-csso@0.2.8","dist":{"shasum":"63fc82ebc842822ce1a8a6c2fb7e78bad72f0cb2","tarball":"https://registry.npmjs.org/gulp-csso/-/gulp-csso-0.2.8.tgz","integrity":"sha512-ID/4oJSMOStl/et6UQ6CbXS2P/duKmA17IET6IkEMDd8EdqbKUMTaVuVG6SSNf1a2wC4ssXtDnIU1sUFe3miBQ==","signatures":[{"keyid":"SHA256:jl3bwswu80PjjokCgh0o2w5c2U4LhQAE57gj9cz1kzA","sig":"MEUCIQDGXbjVl1SSZW4IUnAZPCdqtKp2G72cRyW+Am9GE8I2pAIgeyQZWX3Vx/cVSgBvCML5tHGTiRjXE90V0lUIzxQNMg0="}]},"_from":".","_npmVersion":"1.4.6","_npmUser":{"name":"beneb","email":"therealbenbriggs@hotmail.com"},"maintainers":[{"name":"beneb","email":"therealbenbriggs@hotmail.com"}],"directories":{}},"0.2.9":{"name":"gulp-csso","version":"0.2.9","description":"Minify CSS with CSSO.","license":"MIT","homepage":"https://github.com/ben-eb/gulp-csso","author":{"name":"Ben Briggs","email":"therealbenbriggs@hotmail.com","url":"http://beneb.info"},"scripts":{"test":"mocha"},"repository":{"type":"git","url":"git://github.com/ben-eb/gulp-csso.git"},"keywords":["gulpplugin","minify","css"],"dependencies":{"csso":"~1.3.11","bufferstreams":"0.0.2","gulp-util":"~2.2.14"},"devDependencies":{"chai":"~1.9.0","clear":"0.0.1","gulp":"~3.6.1","gulp-mocha":"~0.4.1","gulp-jshint":"~1.5.0","jshint-stylish":"~0.1.5","mocha":"~1.18.2","event-stream":"~3.1.0"},"main":"index.js","gitHead":"0652849c228ba56ace7fc95f6a6ab63dbf383a68","bugs":{"url":"https://github.com/ben-eb/gulp-csso/issues"},"_id":"gulp-csso@0.2.9","_shasum":"ae96bde7459b41612ec694a4a877c0848e9dd8f4","_from":".","_npmVersion":"1.4.13","_npmUser":{"name":"beneb","email":"therealbenbriggs@hotmail.com"},"maintainers":[{"name":"beneb","email":"therealbenbriggs@hotmail.com"}],"dist":{"shasum":"ae96bde7459b41612ec694a4a877c0848e9dd8f4","tarball":"https://registry.npmjs.org/gulp-csso/-/gulp-csso-0.2.9.tgz","integrity":"sha512-44izvBURdMGtpv2dvP3vhenzpKNerJPtxG2JgkJGJNHn8amLMuPWgHzYiCvjri64GWaHm7L/Zlykqp6Gv+cTnQ==","signatures":[{"keyid":"SHA256:jl3bwswu80PjjokCgh0o2w5c2U4LhQAE57gj9cz1kzA","sig":"MEUCIANV0677oqhsxBZBNnE3mGJ8qGF06xPN8O7aCX/Ql+qlAiEAueG+TC5aZGeFRJ1CiP9YIFCTI9FkBEGp8pYaxlIZ4FQ="}]},"directories":{}},"1.0.0":{"name":"gulp-csso","version":"1.0.0","description":"Minify CSS with CSSO.","license":"MIT","homepage":"https://github.com/ben-eb/gulp-csso","author":{"name":"Ben Briggs","email":"therealbenbriggs@hotmail.com","url":"http://beneb.info"},"scripts":{"test":"mocha"},"repository":{"type":"git","url":"git://github.com/ben-eb/gulp-csso.git"},"keywords":["gulpplugin","minify","css"],"dependencies":{"csso":"~1.3.11","gulp-util":"~3.0.2"},"devDependencies":{"chai":"~1.10.0","event-stream":"~3.2.1","gulp":"~3.8.10","gulp-jshint":"~1.9.0","jshint-stylish":"~1.0.0","mocha":"^2.1.0"},"main":"index.js","gitHead":"4cbe89b27dc3f6a138de9b639c65fafc8dafa5d0","bugs":{"url":"https://github.com/ben-eb/gulp-csso/issues"},"_id":"gulp-csso@1.0.0","_shasum":"93ece6b1138d323a152db8c89add65f5e56ec4c9","_from":".","_npmVersion":"2.1.11","_nodeVersion":"0.10.33","_npmUser":{"name":"beneb","email":"therealbenbriggs@hotmail.com"},"maintainers":[{"name":"beneb","email":"therealbenbriggs@hotmail.com"}],"dist":{"shasum":"93ece6b1138d323a152db8c89add65f5e56ec4c9","tarball":"https://registry.npmjs.org/gulp-csso/-/gulp-csso-1.0.0.tgz","integrity":"sha512-N3yQRZEHjEjd3888ta8n4KC264EHKW98acyac4HXyjWVEtfK7tt1Bifo4LPL1IEe0nLyZZHVKDxItIkmNnB2Hw==","signatures":[{"keyid":"SHA256:jl3bwswu80PjjokCgh0o2w5c2U4LhQAE57gj9cz1kzA","sig":"MEUCIQCdkiIWysFyhVGAXf8Y0EaypLLFZRV9XooTRuz4gkNC4AIgA8xRocHdLO3YqhcN65z4LgUxwuonU6dI2o062iLeQwQ="}]},"directories":{}},"1.0.1":{"name":"gulp-csso","version":"1.0.1","description":"Minify CSS with CSSO.","license":"MIT","files":["index.js","LICENSE-MIT"],"homepage":"https://github.com/ben-eb/gulp-csso","author":{"name":"Ben Briggs","email":"beneb.info@gmail.com","url":"http://beneb.info"},"scripts":{"test":"tape test.js | tap-spec"},"repository":{"type":"git","url":"git+https://github.com/ben-eb/gulp-csso.git"},"keywords":["gulpplugin","minify","css"],"dependencies":{"csso":"^1.4.0","gulp-util":"^3.0.6"},"devDependencies":{"tap-spec":"^4.1.0","tape":"^4.2.1"},"main":"index.js","gitHead":"b360e682003e412fa645009c0cffd398bc9d8072","bugs":{"url":"https://github.com/ben-eb/gulp-csso/issues"},"_id":"gulp-csso@1.0.1","_shasum":"3f5b2bef813ac29fabcb800c1c335acfd980a1bc","_from":".","_npmVersion":"2.12.1","_nodeVersion":"2.3.4","_npmUser":{"name":"beneb","email":"beneb.info@gmail.com"},"dist":{"shasum":"3f5b2bef813ac29fabcb800c1c335acfd980a1bc","tarball":"https://registry.npmjs.org/gulp-csso/-/gulp-csso-1.0.1.tgz","integrity":"sha512-CpkIh7pGwcOVOWgyvYXC0414PjhmwxYi7/3gpc6MhEHXKMRGi00s/b11nIQZU19ieT025kNdMDcfE8cLvSH3pw==","signatures":[{"keyid":"SHA256:jl3bwswu80PjjokCgh0o2w5c2U4LhQAE57gj9cz1kzA","sig":"MEYCIQCK9uz8jTw/TC2FQTW8wX28tV0ZE4qXMKKwRgdO1h0ywAIhAKIol//i+PQVX3w5DgiOejweq0kFIqfU/2SoH62fw+sw"}]},"maintainers":[{"name":"beneb","email":"therealbenbriggs@hotmail.com"}],"directories":{}},"1.1.0":{"name":"gulp-csso","version":"1.1.0","description":"Minify CSS with CSSO.","license":"MIT","files":["index.js","LICENSE-MIT"],"homepage":"https://github.com/ben-eb/gulp-csso","author":{"name":"Ben Briggs","email":"beneb.info@gmail.com","url":"http://beneb.info"},"scripts":{"test":"tape test.js | tap-spec"},"repository":{"type":"git","url":"git+https://github.com/ben-eb/gulp-csso.git"},"keywords":["gulpplugin","minify","css"],"dependencies":{"csso":"^1.6.3","gulp-util":"^3.0.6","vinyl-sourcemaps-apply":"^0.2.1"},"devDependencies":{"tap-spec":"^4.1.0","tape":"^4.2.1"},"main":"index.js","gitHead":"aa7a4fa745a4556bfe2db042912b973ba1bbbce0","bugs":{"url":"https://github.com/ben-eb/gulp-csso/issues"},"_id":"gulp-csso@1.1.0","_shasum":"80d2a8c4c7c9623450c838fbdb9923a14ea210f5","_from":".","_npmVersion":"3.3.12","_nodeVersion":"5.4.1","_npmUser":{"name":"beneb","email":"beneb.info@gmail.com"},"dist":{"shasum":"80d2a8c4c7c9623450c838fbdb9923a14ea210f5","tarball":"https://registry.npmjs.org/gulp-csso/-/gulp-csso-1.1.0.tgz","integrity":"sha512-uVN5YHnbo2Wdx0ghzHEKdrre4fO4h1c320iSi3ucHIAMSjsZmgEcsepRw6Y863+l3waJqP3vrTqA/y0E6Rqgzw==","signatures":[{"keyid":"SHA256:jl3bwswu80PjjokCgh0o2w5c2U4LhQAE57gj9cz1kzA","sig":"MEYCIQD/EZK3q/DRBxG/CS9DI9J5W7ug/WIhXfT5KMjSrCdgiQIhAJw+dwXvkcFGb/79zyXbMXLPdeOIi/UlNt9+c79N6Q+5"}]},"maintainers":[{"name":"beneb","email":"therealbenbriggs@hotmail.com"}],"_npmOperationalInternal":{"host":"packages-5-east.internal.npmjs.com","tmp":"tmp/gulp-csso-1.1.0.tgz_1456830844007_0.7902366265188903"},"directories":{}},"2.0.0":{"name":"gulp-csso","version":"2.0.0","description":"Minify CSS with CSSO.","license":"MIT","files":["index.js","LICENSE-MIT"],"homepage":"https://github.com/ben-eb/gulp-csso","author":{"name":"Ben Briggs","email":"beneb.info@gmail.com","url":"http://beneb.info"},"scripts":{"test":"tape test.js | tap-spec"},"repository":{"type":"git","url":"git+https://github.com/ben-eb/gulp-csso.git"},"keywords":["gulpplugin","minify","css"],"dependencies":{"csso":"^2.0.0","gulp-util":"^3.0.6","vinyl-sourcemaps-apply":"^0.2.1"},"devDependencies":{"tap-spec":"^4.1.0","tape":"^4.2.1"},"main":"index.js","gitHead":"0b6fd28691aafb13468277562abca808d091f64e","bugs":{"url":"https://github.com/ben-eb/gulp-csso/issues"},"_id":"gulp-csso@2.0.0","_shasum":"3237bc949736cd6704c929ca3952ce071021ed84","_from":".","_npmVersion":"3.3.12","_nodeVersion":"5.4.1","_npmUser":{"name":"beneb","email":"beneb.info@gmail.com"},"dist":{"shasum":"3237bc949736cd6704c929ca3952ce071021ed84","tarball":"https://registry.npmjs.org/gulp-csso/-/gulp-csso-2.0.0.tgz","integrity":"sha512-Cq45tvrh9aBByHddCi53vK4tOB5LnBsQWPwg4ypsaHbb8j7wrbWl6uwgTyjHU8LWgO8Jl4sVHxTZeMuaZgh8UA==","signatures":[{"keyid":"SHA256:jl3bwswu80PjjokCgh0o2w5c2U4LhQAE57gj9cz1kzA","sig":"MEUCIH/0BygiHCt4fWdv34pEgPhn8HLzvhiIgWDgm1nOGnJHAiEAp+zmlcVH5rYchZGCnM/HaRMaOJAJRDpwWjWnn3l91rA="}]},"maintainers":[{"name":"beneb","email":"therealbenbriggs@hotmail.com"}],"_npmOperationalInternal":{"host":"packages-16-east.internal.npmjs.com","tmp":"tmp/gulp-csso-2.0.0.tgz_1460227699221_0.9278065329417586"},"directories":{}},"3.0.0":{"name":"gulp-csso","version":"3.0.0","description":"Minify CSS with CSSO.","license":"MIT","files":["index.js","LICENSE-MIT"],"homepage":"https://github.com/ben-eb/gulp-csso","author":{"name":"Ben Briggs","email":"beneb.info@gmail.com","url":"http://beneb.info"},"scripts":{"test":"tape test.js | tap-spec"},"repository":{"type":"git","url":"git+https://github.com/ben-eb/gulp-csso.git"},"keywords":["gulpplugin","minify","css"],"dependencies":{"csso":"^3.0.0","gulp-util":"^3.0.6","vinyl-sourcemaps-apply":"^0.2.1"},"devDependencies":{"tap-spec":"^4.1.0","tape":"^4.2.1"},"main":"index.js","gitHead":"7891fc85893fe72fcf2520cc423b1bb9b1b94e4e","bugs":{"url":"https://github.com/ben-eb/gulp-csso/issues"},"_id":"gulp-csso@3.0.0","_shasum":"13d0add6663f4ca398f4d414ff8dcc349b219b2c","_from":".","_npmVersion":"3.10.8","_nodeVersion":"6.9.1","_npmUser":{"name":"beneb","email":"beneb.info@gmail.com"},"dist":{"shasum":"13d0add6663f4ca398f4d414ff8dcc349b219b2c","tarball":"https://registry.npmjs.org/gulp-csso/-/gulp-csso-3.0.0.tgz","integrity":"sha512-cn6IFtLywD4z7stwwE6cmQMPfLq4/XTVpmXIvBYmveY2igdnaIe4TZCkeT/8KM34yXgs3Iarb6Wxt7Cpr3pozQ==","signatures":[{"keyid":"SHA256:jl3bwswu80PjjokCgh0o2w5c2U4LhQAE57gj9cz1kzA","sig":"MEUCIHMUTGEx4shKNLOAilRTWUMpSXKBmTpqS8CHrAHDQcWUAiEA6B2Cq5Mu1twXCIYFuLVTcuCWe1OXqkDu796y2Wks5Wk="}]},"maintainers":[{"name":"beneb","email":"therealbenbriggs@hotmail.com"}],"_npmOperationalInternal":{"host":"packages-18-east.internal.npmjs.com","tmp":"tmp/gulp-csso-3.0.0.tgz_1489492645434_0.2734903523232788"},"directories":{}},"3.0.1":{"name":"gulp-csso","version":"3.0.1","description":"Minify CSS with CSSO.","license":"MIT","files":["index.js","LICENSE-MIT"],"homepage":"https://github.com/ben-eb/gulp-csso","author":{"name":"Ben Briggs","email":"beneb.info@gmail.com","url":"http://beneb.info"},"scripts":{"test":"tape test.js | tap-spec"},"repository":{"type":"git","url":"git+https://github.com/ben-eb/gulp-csso.git"},"keywords":["gulpplugin","minify","css"],"dependencies":{"csso":"^3.0.0","plugin-error":"^0.1.2","vinyl-sourcemaps-apply":"^0.2.1"},"devDependencies":{"tap-spec":"^4.1.0","tape":"^4.2.1","vinyl":"^2.1.0"},"main":"index.js","gitHead":"9d07cc6307a053c731cac75eeea8672f7d97ee91","bugs":{"url":"https://github.com/ben-eb/gulp-csso/issues"},"_id":"gulp-csso@3.0.1","_npmVersion":"5.6.0","_nodeVersion":"8.8.0","_npmUser":{"name":"lahmatiy","email":"rdvornov@gmail.com"},"dist":{"integrity":"sha512-zhkvq06x1SJrpBN8YNJfc1PDono2+xjB6nI9UmBPh88nS4Weuz0hZMgJ4YruOw9Bf+oDrX71U6pkos6pIQhc1g==","shasum":"3c160364491e32f2ecefd5d531cf7724f1afb7f0","tarball":"https://registry.npmjs.org/gulp-csso/-/gulp-csso-3.0.1.tgz","signatures":[{"keyid":"SHA256:jl3bwswu80PjjokCgh0o2w5c2U4LhQAE57gj9cz1kzA","sig":"MEUCIQDm89HPwLt2g1kGAgh+U6f36f4/AFfn3mm80FWmBxRqlAIgNh+YpQ1vRfquOi6Ky71jh1RPph/zFr2pfmVI5HAoSmM="}]},"maintainers":[{"email":"rdvornov@gmail.com","name":"lahmatiy"},{"email":"beneb.info@gmail.com","name":"beneb"}],"_npmOperationalInternal":{"host":"s3://npm-registry-packages","tmp":"tmp/gulp-csso-3.0.1.tgz_1515145255555_0.6947644064202905"},"directories":{}},"4.0.0":{"name":"gulp-csso","version":"4.0.0","description":"Minify CSS with CSSO.","license":"MIT","homepage":"https://github.com/ben-eb/gulp-csso","author":{"name":"Ben Briggs","email":"beneb.info@gmail.com","url":"http://beneb.info"},"scripts":{"test":"tape test.js | tap-spec"},"repository":{"type":"git","url":"git+https://github.com/ben-eb/gulp-csso.git"},"keywords":["gulpplugin","minify","css"],"dependencies":{"csso":"^4.0.0","plugin-error":"^1.0.0","vinyl-sourcemaps-apply":"^0.2.1"},"devDependencies":{"tap-spec":"^5.0.0","tape":"^4.2.1","vinyl":"^2.1.0"},"main":"index.js","engines":{"node":">=8.0.0"},"gitHead":"67710f1fbeb83c68918bd36280843143e2e1e617","bugs":{"url":"https://github.com/ben-eb/gulp-csso/issues"},"_id":"gulp-csso@4.0.0","_nodeVersion":"12.13.0","_npmVersion":"6.12.0","dist":{"integrity":"sha512-kXXRzi2OD79t74gKVkTZGWLnuB3XPLAcDMRmug6y4m/n8I7RhKYaWYP6W2XxAdIVUP1NYYLYqRmeYokZPaLznA==","shasum":"14d8cd24893ec64f2aa08b84fe0d32759c23aeca","tarball":"https://registry.npmjs.org/gulp-csso/-/gulp-csso-4.0.0.tgz","fileCount":5,"unpackedSize":7748,"npm-signature":"-----BEGIN PGP SIGNATURE-----\r\nVersion: OpenPGP.js v3.0.4\r\nComment: https://openpgpjs.org\r\n\r\nwsFcBAEBCAAQBQJdzS5SCRA9TVsSAnZWagAANioP/ioKNhpPDZPxTIncIkhS\nFGQf1UK08Hhz/5UaZsqq4hPuxSixVlNWOmek+YbRb5Nj1ZMBnPc7O16TKc3N\n46nJq0wtj7pZL0WkMbBCHfEJBuVsNlQr7D/9396m9GZCySGaodtcw6c+JHWz\nld0wkBrKYPjwRGnDW43cSPlXCoBOHPRYZ4vSzrcZN+livBxJPzf59L/qIIjv\neHy8P9Q9w0Rb0svnmNDT7Fhb1dNQKdRe3zRCX7LOpwkycbpakJ0/FU7vq4SW\n0ASPAZU7iPDyjKEDDDMDrHt+KyXnVEgJ7/pqltjQU7u/yNzz8PIE2BCEbLPI\nnTJl2S1fm84Q2mgRwfR13Vuoak0QFO3RxIx6lMcIsqrPhCboqkBaq91vMOKj\njwokRwzAc1dXz/XTjydKA9IEcQeKQI0o//gCa5un1YEI1YsNjlzdn51801YE\np01Ug9IsykKpkV1I222xp1qOI15tQVsi65LNd4VBJ7rlAKpEbnS6c/8+GM7C\nxCjsgK2UckGnRU36rf2OlB7hjyO51XqphwSrqvqayEZrUozh0/8pFhLlXNs0\nxFZW+52FPlg4WEU1uvMeYkZ/VLq4HPojerhDDJn+TeXLIedKOIhs5fnMPSd+\nZvq9TxPlzI+CBR80LpNp+XSctunxHzUenR9x8cfAVXLV1AL6X1fmJvFfM8U9\ne5BB\r\n=Jp69\r\n-----END PGP SIGNATURE-----\r\n","signatures":[{"keyid":"SHA256:jl3bwswu80PjjokCgh0o2w5c2U4LhQAE57gj9cz1kzA","sig":"MEYCIQDIJi1VHKLclIYXVWrGabnkDPSFmHuGDUAuaRzhTzyQnwIhAO/Nr2OnNUMp1ktxc7jUAqfustMshWoI8F7hctnvFCZP"}]},"maintainers":[{"email":"beneb.info@gmail.com","name":"beneb"},{"email":"rdvornov@gmail.com","name":"lahmatiy"}],"_npmUser":{"name":"lahmatiy","email":"rdvornov@gmail.com"},"directories":{},"_npmOperationalInternal":{"host":"s3://npm-registry-packages","tmp":"tmp/gulp-csso_4.0.0_1573727825893_0.4664824063499726"},"_hasShrinkwrap":false},"4.0.1":{"name":"gulp-csso","version":"4.0.1","description":"Minify CSS with CSSO.","license":"MIT","homepage":"https://github.com/ben-eb/gulp-csso","author":{"name":"Ben Briggs","email":"beneb.info@gmail.com","url":"http://beneb.info"},"scripts":{"test":"tape test.js | tap-spec"},"repository":{"type":"git","url":"git+https://github.com/ben-eb/gulp-csso.git"},"keywords":["gulpplugin","minify","css"],"dependencies":{"csso":"^4.0.0","plugin-error":"^1.0.0","vinyl-sourcemaps-apply":"^0.2.1"},"devDependencies":{"tap-spec":"^5.0.0","tape":"^4.2.1","vinyl":"^2.1.0"},"main":"index.js","engines":{"node":">=8.0.0"},"gitHead":"f758a8cb6e3563e0e02483d9d9cce3492ce64198","bugs":{"url":"https://github.com/ben-eb/gulp-csso/issues"},"_id":"gulp-csso@4.0.1","_nodeVersion":"13.1.0","_npmVersion":"6.12.1","dist":{"integrity":"sha512-Kg8gqmd6XcUlMTdBbqdCEcpHumc8ytc4khgm9AXeCjl8eHx7b6tC11y8haizFI+Zw/cSHL6HCj7GwGLwxxBUFQ==","shasum":"c2ac2b5f7138ed04073ed8f7cf89c12f716580d0","tarball":"https://registry.npmjs.org/gulp-csso/-/gulp-csso-4.0.1.tgz","fileCount":5,"unpackedSize":7857,"npm-signature":"-----BEGIN PGP SIGNATURE-----\r\nVersion: OpenPGP.js v3.0.13\r\nComment: https://openpgpjs.org\r\n\r\nwsFcBAEBCAAQBQJh2s0yCRA9TVsSAnZWagAAITsQAJEddH9KjO1AxGJtop2B\nLeLggPUzTGjGu7XBG5BARi8P9zS0IgZuBTta0yor48zWKD2pQzx2vAuveC8N\nHo3U2jSS9oJBCVt6e0CpoKEgEURoJCluKT5Wahpr/VYlQnFyQh2eSAEqiV3b\nxNd77LycXLixNyOxdlY6hl0FWAP7+roW7Aityz7TjdZIM93h/WkgC0XFZQ0D\nPtoe/CNj+2CNXLRq5D4zigNQzA5cGHIoNT0OlBfHu3bxlVIQr0YdIK9h0Oco\nkO/kXw7Yg4C7etDC6xV0ew0dSOStW1lEqp2BQtyw4v8LJ6UD/1HKlPNcfeR1\norYS8d0mITv0SMWO43uHER8rZ7WiNQdmgsdu8egP2jZRWngV9W47jKxEF2GR\nP+xJ7RNjRvLFuySsAXR5llRHlE5Hc0DErn26U84VOb9bwQ5k8bqzd3J+Lz4a\n7z47b4FnkW6Lzn6BQt2xFVg+wB5+zXxv7eQKnKoTa9vPWNsNZorFYWfSKBHD\nx+puhCdogo+UCZ+6/UuV5IDvo6VjBenQM/0JxfJHFJ/Km2uOvPe2a2ZmcSlQ\nngQBhLC/R5DZqcaX1s3+6ro/8L9rUhQOF/p8niwGm+hs1SPpE8jukbi8dLiY\nym58nuXFFUGUkV1AHhucOAp4M057SRUj0hS0UVul69fCz+wCxIhCddRUnEvl\nwPIO\r\n=j9NV\r\n-----END PGP SIGNATURE-----\r\n","signatures":[{"keyid":"SHA256:jl3bwswu80PjjokCgh0o2w5c2U4LhQAE57gj9cz1kzA","sig":"MEYCIQCf6/duwCtOEnge2cVKiRgFoSMeTtyMsDYw5fnmi+I9awIhAIifZG1dLYGaUTfHZTHmVKw4OB4D2tTWkzLqXD0YjYts"}]},"maintainers":[{"email":"beneb.info@gmail.com","name":"beneb"},{"email":"rdvornov@gmail.com","name":"lahmatiy"}],"_npmUser":{"name":"lahmatiy","email":"rdvornov@gmail.com"},"directories":{},"_npmOperationalInternal":{"host":"s3://npm-registry-packages","tmp":"tmp/gulp-csso_4.0.1_1573736279146_0.37790269802825205"},"_hasShrinkwrap":false}},"readme":"# [gulp](https://github.com/gulpjs/gulp)-csso [![Build Status](https://travis-ci.org/ben-eb/gulp-csso.svg?branch=master)](https://travis-ci.org/ben-eb/gulp-csso) [![NPM version](https://badge.fury.io/js/gulp-csso.svg)](http://badge.fury.io/js/gulp-csso) [![Dependency Status](https://gemnasium.com/ben-eb/gulp-csso.svg)](https://gemnasium.com/ben-eb/gulp-csso)\n\n> Minify CSS with [CSSO](https://www.npmjs.com/package/csso).\n\n*If you have any difficulties with the output of this plugin, please use\nthe [CSSO tracker](https://github.com/css/csso/issues).*\n\n## Install\n\nWith [npm](https://www.npmjs.com/package/gulp-csso) do:\n\n```\nnpm install gulp-csso --save-dev\n```\n\n## Example\n\n```js\nvar gulp = require('gulp');\nvar csso = require('gulp-csso');\n\ngulp.task('default', function () {\n    return gulp.src('./main.css')\n        .pipe(csso())\n        .pipe(gulp.dest('./out'));\n});\n\ngulp.task('development', function () {\n    return gulp.src('./main.css')\n        .pipe(csso({\n            restructure: false,\n            sourceMap: true,\n            debug: true\n        }))\n        .pipe(gulp.dest('./out'));\n});\n```\n\n## API\n\n### csso([options])\n\n#### options\n\nFor backwards compatibility it can also be a `boolean`. In this case, the\ninverted value is set to `options.restructure`\n(e.g. `true` becomes `{restructure: false}`).\n\n##### restructure\n\nType: `boolean`  \nDefault: `true`\n\nThe default is to use structure minimization for maximum compression.\nPass `false` instead if you want to disable this feature.\n\n##### sourceMap\n\nType: `boolean`  \nDefault: depends on input file has a source map or not\n\nSpecify this to generate source map; by default a source map is generated only\nif the input file has a source map. Pass `true` to ensure that the source map\nis generated or `false` to disable this.\n\nAlternatively, you can enable source maps support using [gulp-sourcemaps]:\n\n[gulp-sourcemaps]: https://github.com/floridoo/gulp-sourcemaps\n\n```js\nvar gulp = require('gulp');\nvar csso = require('gulp-csso');\nvar sourcemaps = require('gulp-sourcemaps');\n\ngulp.task('default', function () {\n    return gulp.src('main.css')\n        .pipe(sourcemaps.init())\n        .pipe(csso())\n        .pipe(sourcemaps.write('.'))\n        .pipe(gulp.dest('./out'));\n});\n```\n\n##### debug\n\nType: `boolean`  \nDefault: `false`\n\nPass `true` or a positive number (greater number for more details) to get some\ndebugging information about the minification process.\n\n##### usage\n\nType: `object`\nDefault: `null`\n\nUsage data for advanced optimisations (read more in the [CSSO documentation](https://github.com/css/csso#usage-data)).\n\n## Contributing\n\nPull requests are welcome. If you add functionality, then please add unit tests\nto cover it.\n\n## License\n\nMIT © [Ben Briggs](http://beneb.info)\n","maintainers":[{"email":"beneb.info@gmail.com","name":"beneb"},{"email":"rdvornov@gmail.com","name":"lahmatiy"}],"time":{"modified":"2022-06-18T16:54:43.723Z","created":"2013-12-05T22:22:58.064Z","0.1.0":"2013-12-05T22:23:01.012Z","0.1.1":"2013-12-06T23:39:59.852Z","0.1.2":"2013-12-15T12:54:38.244Z","0.1.3":"2013-12-31T17:05:58.385Z","0.1.4":"2014-01-01T01:05:19.889Z","0.1.5":"2014-01-04T23:22:46.830Z","0.1.6":"2014-01-05T17:48:28.171Z","0.1.7":"2014-01-07T22:17:18.226Z","0.1.8":"2014-01-17T23:29:14.709Z","0.2.0":"2014-01-21T23:21:19.881Z","0.2.1":"2014-01-21T23:23:56.578Z","0.2.2":"2014-01-23T23:22:51.393Z","0.2.3":"2014-01-28T12:06:52.198Z","0.2.4":"2014-02-20T23:06:10.072Z","0.2.5":"2014-02-23T17:09:15.919Z","0.2.6":"2014-02-24T21:49:00.982Z","0.2.7":"2014-04-04T20:19:32.270Z","0.2.8":"2014-04-21T15:18:04.514Z","0.2.9":"2014-06-02T05:50:14.233Z","1.0.0":"2015-01-28T17:59:49.946Z","1.0.1":"2015-10-17T22:36:29.375Z","1.1.0":"2016-03-01T11:14:06.050Z","2.0.0":"2016-04-09T18:48:20.288Z","3.0.0":"2017-03-14T11:57:26.028Z","3.0.1":"2018-01-05T09:40:56.397Z","4.0.0":"2019-11-14T10:37:06.005Z","4.0.1":"2019-11-14T12:57:59.299Z"},"author":{"name":"Ben Briggs","email":"beneb.info@gmail.com","url":"http://beneb.info"},"repository":{"type":"git","url":"git+https://github.com/ben-eb/gulp-csso.git"},"readmeFilename":"README.md","homepage":"https://github.com/ben-eb/gulp-csso","keywords":["gulpplugin","minify","css"],"bugs":{"url":"https://github.com/ben-eb/gulp-csso/issues"},"license":"MIT","users":{"growdigital":true,"wayneseymour":true,"romelyus":true,"rubenlozano":true,"ijy":true,"richarddavenport":true,"icflorescu":true,"ericwbailey":true,"zoxon":true,"evan2x":true,"joaocunha":true,"riszw":true,"dockawash":true,"itonyyo":true,"ginof":true,"dominikkucharski":true,"arahnoid":true,"danrootdesign":true,"mrtwister":true,"jruif":true,"ne0":true,"dwayneford":true,"gudvinr":true,"maskedcoder":true,"fotooo":true,"kbradl16":true,"skl":true,"edwin_estrada":true,"gollojs":true,"mjurincic":true,"hema":true,"bob.cody":true,"jerkovicl":true,"herkulano":true,"vmsynkov":true,"noderat":true,"bebaps":true,"arttse":true,"bian17888":true,"akash_shah":true,"temoto-kun":true,"vvilardell":true,"fanus":true,"nicolasgodefroy7":true,"dennisli87":true,"jimco":true,"king.v":true,"itsmeara":true,"magicboy":true,"skrdv":true,"vragovr":true,"iori20091101":true,"krawster":true,"paulnordlund":true,"louiskenzo":true,"evandrosevergnini":true,"nickolas_sv":true,"mskjp":true,"scassady":true,"rajakannan":true,"anderpo":true,"ruslan.garaev":true,"ironclad.soul":true,"iamninad":true,"y_r0925":true,"rain-again":true,"sergioscabuzzo":true,"irj":true,"morderdesign":true,"vivekm":true,"eugene.korniets":true},"_etag":"W/\"89226e2a3fbf9c96f22d091d387d01a2\"","_lastModified":"Sat, 18 Jun 2022 16:54:45 GMT"}